ShenduXuexiKuaisuCankaoChuyiFix1/README.md
ShenduXuexiKuaisuCankaoChuyiFix1/__init__.py
ShenduXuexiKuaisuCankaoChuyiFix1/__main__.py
ShenduXuexiKuaisuCankaoChuyiFix1/file.epub
ShenduXuexiKuaisuCankaoChuyiFix1/index.html
ShenduXuexiKuaisuCankaoChuyiFix1/css/__init__.py
ShenduXuexiKuaisuCankaoChuyiFix1/css/annotations.css
ShenduXuexiKuaisuCankaoChuyiFix1/css/main.css
ShenduXuexiKuaisuCankaoChuyiFix1/css/normalize.css
ShenduXuexiKuaisuCankaoChuyiFix1/css/popup.css
ShenduXuexiKuaisuCankaoChuyiFix1/font/__init__.py
ShenduXuexiKuaisuCankaoChuyiFix1/font/fontello.eot
ShenduXuexiKuaisuCankaoChuyiFix1/font/fontello.svg
ShenduXuexiKuaisuCankaoChuyiFix1/font/fontello.ttf
ShenduXuexiKuaisuCankaoChuyiFix1/font/fontello.woff
ShenduXuexiKuaisuCankaoChuyiFix1/img/__init__.py
ShenduXuexiKuaisuCankaoChuyiFix1/img/annotator-glyph-sprite.png
ShenduXuexiKuaisuCankaoChuyiFix1/img/annotator-icon-sprite.png
ShenduXuexiKuaisuCankaoChuyiFix1/img/apple-touch-icon.png
ShenduXuexiKuaisuCankaoChuyiFix1/img/cancelfullscreen.png
ShenduXuexiKuaisuCankaoChuyiFix1/img/close.png
ShenduXuexiKuaisuCankaoChuyiFix1/img/fullscreen.png
ShenduXuexiKuaisuCankaoChuyiFix1/img/loader.gif
ShenduXuexiKuaisuCankaoChuyiFix1/img/menu-icon.png
ShenduXuexiKuaisuCankaoChuyiFix1/img/save.png
ShenduXuexiKuaisuCankaoChuyiFix1/img/saved.png
ShenduXuexiKuaisuCankaoChuyiFix1/img/settings-s.png
ShenduXuexiKuaisuCankaoChuyiFix1/img/settings.png
ShenduXuexiKuaisuCankaoChuyiFix1/img/star.png
ShenduXuexiKuaisuCankaoChuyiFix1/js/__init__.py
ShenduXuexiKuaisuCankaoChuyiFix1/js/epub.js
ShenduXuexiKuaisuCankaoChuyiFix1/js/epub.min.js
ShenduXuexiKuaisuCankaoChuyiFix1/js/epub.min.map
ShenduXuexiKuaisuCankaoChuyiFix1/js/hooks.min.js
ShenduXuexiKuaisuCankaoChuyiFix1/js/hooks.min.map
ShenduXuexiKuaisuCankaoChuyiFix1/js/reader.js
ShenduXuexiKuaisuCankaoChuyiFix1/js/reader.js.map
ShenduXuexiKuaisuCankaoChuyiFix1/js/reader.min.js
ShenduXuexiKuaisuCankaoChuyiFix1/js/reader.min.map
ShenduXuexiKuaisuCankaoChuyiFix1/js/hooks/__init__.py
shendu_xuexi_kuaisu_cankao_chuyi_fix1-2025.3.24.1.dist-info/METADATA
shendu_xuexi_kuaisu_cankao_chuyi_fix1-2025.3.24.1.dist-info/WHEEL
shendu_xuexi_kuaisu_cankao_chuyi_fix1-2025.3.24.1.dist-info/entry_points.txt
shendu_xuexi_kuaisu_cankao_chuyi_fix1-2025.3.24.1.dist-info/top_level.txt
shendu_xuexi_kuaisu_cankao_chuyi_fix1-2025.3.24.1.dist-info/RECORD
